deepprojection/GUI.py
deepprojection/ProjNet.py
deepprojection/__init__.py
deepprojection/__main__.py
deepprojection/data.py
deepprojection/postprocess.py
deepprojection/predict.py
deepprojection/project.py
deepprojection/train.py
deepprojection/utils.py
deepprojection-1.0.0.dist-info/LICENSE
deepprojection-1.0.0.dist-info/WHEEL
deepprojection-1.0.0.dist-info/METADATA
deepprojection-1.0.0.dist-info/RECORD
