Metadata-Version: 2.1
Name: deepprojection
Version: 1.0.0
Summary: Trainable projection of 3D microscopy stacks using deep learning
License: GPL-3.0-only
Author: Daniel Haertter
Author-email: dani.hae@posteo.de
Requires-Python: >=3.8,<4.0
Classifier: License :: OSI Approved :: GNU General Public License v3 (GPLv3)
Classifier: Programming Language :: Python :: 3
Classifier: Programming Language :: Python :: 3.10
Classifier: Programming Language :: Python :: 3.8
Classifier: Programming Language :: Python :: 3.9
Requires-Dist: albumentations (>=0.4,<0.5)
Requires-Dist: barbar (>=0.2,<0.3)
Requires-Dist: numpy (>=1.18,<2.0)
Requires-Dist: tifffile
Requires-Dist: tqdm (>=4.61,<5.0)
